{
    "legacy_addon_id": "",
    "title": "[TC] Payment Profile Order",
    "description": "Adds ability to sort payment profiles",
    "version_id": 1000070,
    "version_string": "1.0.0",
    "dev": "TeslaCloud Studios LLC",
    "dev_url": "https://teslacloud.net",
    "faq_url": "",
    "support_url": "https://teslacloud.net/forums/xf-addon_ppo/",
    "extra_urls": {
        "inzanty": "https://teslacloud.net/members/inzanty.213/"
    },
    "require": {
        "XF": [
            2010070,
            "XenForo 2.1.0+"
        ]
    },
    "icon": "icon.png"
}